README.md
setup.py
surveyJsUnofficial/__init__.py
surveyJsUnofficial/surveyJs.py
surveyJsUnofficial.egg-info/PKG-INFO
surveyJsUnofficial.egg-info/SOURCES.txt
surveyJsUnofficial.egg-info/dependency_links.txt
surveyJsUnofficial.egg-info/top_level.txt