Metadata-Version: 1.1
Name: surveyJsUnofficial
Version: 0.0.1
Summary: A basic library to access surveyJs api.
Home-page: UNKNOWN
Author: Pramod Gaikwad
Author-email: UNKNOWN
License: UNKNOWN
Keywords: surveyJs python survey free
Platform: UNKNOWN
Classifier: Development Status :: 5 - Production/Stable
Classifier: Intended Audience :: Education
Classifier: Operating System :: Microsoft :: Windows :: Windows 10
Classifier: License :: OSI Approved :: MIT License
Classifier: Programming Language :: Python :: 3
